pathobs/__init__.py
pathobs/obstacle.py
pathobs/path.py
pathobs/path_analyzer.py
pathobs/scenario.py
pathobs-0.1.7.dist-info/LICENSE
pathobs-0.1.7.dist-info/METADATA
pathobs-0.1.7.dist-info/WHEEL
pathobs-0.1.7.dist-info/top_level.txt
pathobs-0.1.7.dist-info/RECORD
