Metadata-Version: 2.1
Name: pathobs
Version: 0.1.7
Summary: Pacote para criar e analisar cenários geométricos.
Home-page: https://github.com/marcelotores
Author: Marcelo Torres
Author-email: marcelotores21@gmail.com
License: UNKNOWN
Platform: UNKNOWN
Classifier: Programming Language :: Python :: 3
Classifier: License :: OSI Approved :: MIT License
Classifier: Operating System :: OS Independent
Requires-Python: >=3.6
License-File: LICENSE
Requires-Dist: matplotlib
Requires-Dist: numpy
Requires-Dist: shapely
